example/runfile_hrmc.py
example/runfile_rmc.py
pyhrmc/__init__.py
pyhrmc/core/__init__.py
pyhrmc/core/energy.py
pyhrmc/core/interpolator.py
pyhrmc/core/rdf.py
pyhrmc/core/rmc.py
pyhrmc/core/rmc_coord.py
pyhrmc/core/structure.py
pyhrmc/other/coordination.py
pyhrmc/other/distances_coordination_voro.py
pyhrmc/other/rmc_autotune.py
pyhrmc/other/rmc_energylim.py
pyhrmc/other/streamlit_app.py
pyhrmc/transformers/__init__.py
pyhrmc/transformers/atom_hop.py
pyhrmc/transformers/base.py
pyhrmc/validators/__init__.py
pyhrmc/validators/base.py
pyhrmc/validators/distances_coordination.py
pyhrmc/validators/distances_coordination_coord.py
pyhrmc/validators/site_distance.py
pyhrmc/validators/slab_thickness.py
pyhrmc/validators/target_density.py
pyhrmc/validators/test.py
pyhrmc-0.1.1.dist-info/licenses/LICENSE.md
tests/test_slab.py
pyhrmc-0.1.1.dist-info/METADATA
pyhrmc-0.1.1.dist-info/WHEEL
pyhrmc-0.1.1.dist-info/top_level.txt
pyhrmc-0.1.1.dist-info/RECORD
