Metadata-Version: 2.4
Name: pyhrmc
Version: 0.1.1
Summary: A Python implementation of Hybrid Reverse Monte Carlo for atomistic modeling from electron total scattering
Home-page: https://github.com/ehrhardtkm/pyHRMC
Author: Karen M. Ehrhardt
Author-email: "Karen M. Ehrhardt" <kme@email.unc.edu>
License: BSD-3-Clause
Project-URL: Homepage, https://github.com/ehrhardtkm/pyHRMC
Project-URL: repository, https://github.com/ehrhardtkm/pyHRMC
Project-URL: documentation, https://ehrhardtkm.github.io/pyHRMC/
Keywords: Hybrid Reverse Monte Carlo,HRMC,Amorphous materials,electron scattering
Classifier: Programming Language :: Python :: 3.11
Classifier: Operating System :: OS Independent
Requires-Python: <3.12,>=3.10
License-File: LICENSE.md
Requires-Dist: ase
Requires-Dist: matminer
Requires-Dist: matplotlib
Requires-Dist: numpy<2
Requires-Dist: pandas
Requires-Dist: pymatgen==2024.2.20
Requires-Dist: pymatgen_analysis_diffusion==2023.8.15
Requires-Dist: scikit_learn==1.2.1
Requires-Dist: scipy
Requires-Dist: setuptools>=61.0
Dynamic: author
Dynamic: home-page
Dynamic: license-file
